{
  "$schema": "http://adaptivecards.io/schemas/adaptive-card.json",
  "type": "AdaptiveCard",
  "version": "1.0",
  "body": [
    
    {
      "type": "TextBlock",
      "spacing": "medium",
      "size": "default",
      "weight": "bolder",
      "text": "Courses Section",
      "wrap": true,
      "maxLines": 0
    },
    {
      "type": "TextBlock",
      "size": "default",
      "isSubtle": true,
      "text": "",
      "wrap": true,
      "maxLines": 0
    }
  ],
  "actions": [
    {
      "type": "Action.Submit",
      "title": "Students in Course",
      "data": "Students in Course",
      "id": "Students in Course"
    }
  ]
}